CherryPie/__init__.py
CherryPie/menu.py
CherryPie-1.0.0.dist-info/LICENSE
CherryPie-1.0.0.dist-info/METADATA
CherryPie-1.0.0.dist-info/WHEEL
CherryPie-1.0.0.dist-info/top_level.txt
CherryPie-1.0.0.dist-info/RECORD
