Metadata-Version: 2.1
Name: CherryPie
Version: 1.0.0
Summary: Build a beautiful CLI application.
Author: Reece Harris
Author-email: reeceharris@email.com
License: GPL-3.0-only
Project-URL: Donate, https://www.buymeacoffee.com/NotReeceHarris
Project-URL: Documentation, https://github.com/NotReeceHarris/CherryPie/wiki
Project-URL: Changes, https://github.com/NotReeceHarris/CherryPie/releases
Project-URL: Source Code, https://github.com/NotReeceHarris/CherryPie
Project-URL: Issue Tracker, https://github.com/NotReeceHarris/CherryPie/issues/
Platform: UNKNOWN
Classifier: Development Status :: 1 - Planning
Classifier: Environment :: Console
Classifier: Intended Audience :: Developers
Classifier: License :: OSI Approved :: GNU General Public License v3 (GPLv3)
Classifier: Operating System :: OS Independent
Classifier: Programming Language :: Python
Classifier: Programming Language :: Python :: 3
Classifier: Operating System :: MacOS :: MacOS X
Classifier: Operating System :: POSIX
Classifier: Operating System :: POSIX :: BSD
Classifier: Operating System :: POSIX :: Linux
Classifier: Operating System :: Microsoft :: Windows
Requires-Python: >=3.7
License-File: LICENSE
